moveread/pipelines/manual_correct/__init__.py
moveread/pipelines/manual_correct/__init__.pyi
moveread/pipelines/manual_correct/main.py
moveread/pipelines/manual_correct/types.py
moveread_pipelines_manual_correct-0.1.8.dist-info/METADATA
moveread_pipelines_manual_correct-0.1.8.dist-info/WHEEL
moveread_pipelines_manual_correct-0.1.8.dist-info/top_level.txt
moveread_pipelines_manual_correct-0.1.8.dist-info/RECORD
