Metadata-Version: 2.1
Name: moveread-pipelines-manual-correct
Version: 0.1.8
Summary: Manual perspective correction pipeline for Moveread
Author-email: Marcel Claramunt <marcel@moveread.com>
Project-URL: repo, https://github.com/moveread/moveread-pipelines.git
Requires-Python: >=3.10
Requires-Dist: queue-api
Requires-Dist: pydantic ==2.*
Requires-Dist: moveread-annotations
Requires-Dist: pure-cv
Requires-Dist: lazy-loader
Requires-Dist: pipeteer
